{"name":"Sale without Products","testSteps":[{"number":1,"description":"[1] {topcat\u003dSale}","duration":18353,"startTime":1469923210320,"screenshots":[{"screenshot":"b6a02dee81ecf7817328efe5a6e601e7.png"}],"result":"SUCCESS","children":[{"number":2,"description":"Given Luma Home Page","duration":10075,"startTime":1469923210320,"screenshots":[{"screenshot":"3f951216a6ec4ae33be75b86580afb62.png"}],"result":"SUCCESS"},{"number":3,"description":"When User Trigger Top Level Entry \"Sale\"","duration":4104,"startTime":1469923220395,"screenshots":[{"screenshot":"3f951216a6ec4ae33be75b86580afb62.png"},{"screenshot":"b6a02dee81ecf7817328efe5a6e601e7.png"}],"result":"SUCCESS"},{"number":4,"description":"Then Page \"Sale\" Header and Footer Elements are Interactive","duration":1801,"startTime":1469923224500,"screenshots":[{"screenshot":"b6a02dee81ecf7817328efe5a6e601e7.png"}],"result":"SUCCESS"},{"number":5,"description":"And Complete LHS and Promo Module is Visible","duration":1745,"startTime":1469923226301,"screenshots":[{"screenshot":"b6a02dee81ecf7817328efe5a6e601e7.png"}],"result":"SUCCESS"}]}],"userStory":{"id":"browse-top-level-category","storyName":"Browse Top Level Category","path":"TopCatView.feature","narrative":"As a User\r\nI want to browse and navigate all Top Level Categories\r\nSo as to view all Page Modules","type":"feature"},"title":"Sale without Products","description":"","backgroundTitle":"","backgroundDescription":"","tags":[{"name":"regression","type":"tag"},{"name":"Browse Top Level Category","type":"feature"},{"name":"topcat","type":"tag"}],"startTime":1469923210319,"duration":18355,"sessionId":"9d860eb2-f9b5-4d56-ba06-ed9fd7f6be2f","driver":"firefox","dataTable":{"headers":["topcat"],"rows":[{"values":["Sale"],"result":"SUCCESS"}],"predefinedRows":true,"currentRow":{"value":0},"dataSetDescriptors":[{"startRow":0,"rowCount":0,"name":"","description":""}]},"manual":false,"result":"SUCCESS"}